cpu.v
module instruction_set_model(
    //MEMORY
    input clk,
    input rst,
    input debug,
    output [6:0] debuger,/*2^7=128*/
    output [11:0] MEM_ADDR,/*ADDRSIZE-1:0*/
    input [0:31] MEM_IN,/*0:WIDTH-1*/
    output [0:31] MEM_OUT,/*0:WIDTH-1*/
    output MEM_CTRL,//0:read | 1:write
    output [11:0] INS_ADDR,
    input [0:31] INS_MEM,//always in read mode

    //-------------------
    output [32:0] reg_debug_out
    //-------------------
);
//parameter CYCLE = 10;//cycle time
parameter WIDTH = 32;//width of data path
parameter ADDRSIZE = 12;//size of address field
//parameter MEMSIZE = (1<<ADDRSIZE/*4096*/);//size of memory (2^ADDRSIZE)=2^12
parameter MAXREGS = 16;//max # of reg.
parameter SBITS = 5;//status reg. bits
//cpu reg.
reg [WIDTH-1:0/*32*/] RFILE[0:MAXREGS-1/*16*/],//Register File
                      ir,//Instruction Register
                      src1, src2 ;//Alu operation registers
reg [WIDTH:0/*33*/] result ;//ALU result register
reg [SBITS-1:0/*5*/] psr;//Processor Status Register
reg [ADDRSIZE-1:0/*12*/] pc ;//Program counter
//reg. for output
reg [ADDRSIZE-1:0] MEM_D ;
//reg [ADDRSIZE-1:0] INS_D ;//<X>
reg [0:WIDTH-1] MEM_O ;
reg MEM_C;
assign MEM_ADDR = MEM_D;
assign INS_ADDR = /*<X>*//*INS_D*/pc;
assign MEM_OUT = MEM_O;
assign MEM_CTRL = MEM_C;
/*debug*/
reg [6:0] debug_r;
assign debuger = debug_r; 
//temp. reg.
reg temp_checkcond;
//define
`define TRUE 1
`define FALSE 0 
/*============================================================
Instruction Format
31      28 27    24 23         12 11            0
+-----------------------------------------------+
| 4bits   |  4bits |   12bits    |    12bits    |
+-----------------------------------------------+
IR[31:28]:OPcode (max # of instructions = 2^4 = 16)
IR[27:24]: condition code  !or!
{
IR[27]:	 source type 0=reg (mem), 1=imm
IR[26]:	 destination type 0=reg (mem), 1=imm (Not valid)
}
IR[23:12]:  source address or	shift/rotate count
IR[11:0] : destination address
============================================================*/
`define OPCODE ir[31:28]
`define SRC ir[23:12]// source addr.
`define DST ir[11:0]// destination addr.
`define SRCTYPE ir[27] // source type, 0=reg, 1=imm
`define DSTTYPE ir[26] // destination type, 0=reg, 1=imm
`define CCODE ir[27:24]
`define SRCNT ir[23:12] // Shift/Rotate count -= left, +=right
// Operand Types
`define REGTYPE 0
`define IMMTYPE 1
// Define opcodes for each instruction
`define NOP 4'b0000 //0
`define BRA 4'b0001 //1
`define LD  4'b0010 //2
`define STR 4'b0011 //3
`define ADD 4'b0100 //4
`define MUL 4'b0101 //5
`define CMP 4'b0110 //6
`define SHF 4'b0111 //7
`define ROT 4'b1000 //8
`define HLT 4'b1001 //9
`define DIV 4'b1010 //10 Division
`define RMD 4'b1011 //11 Remainder
// Define Condition Code fields
`define CARRY psr[0]
`define EVEN psr[1] // if x is even, x%2 (in C language) = 0
`define PARITY psr[2] // the fact of being even or odd. <!>
`define ZERO psr[3]
`define NEG psr[4] //Negative 
// Define Condition Codes <!>
`define CCC 1 // Result has carry
`define CCE 2 // Result is even
`define CCP 3 // Result is odd parity
`define CCZ 4 // Result is Zero
`define CCN 5 // Result is Negative
`define CCA 0 // Always
//L/R
`define RIGHT  0 // Rotate/Shift Right
`define LEFT   1 // Rotate/Shift Left
//Unsynthesizable//<?>
//integer
integer i;

//--------------------------------------------
reg [32:0] reg_debug_o;
assign reg_debug_out = reg_debug_o;
//--------------------------------------------

//function
function [6:0] setcondcode;//Compute the condition codes and set PSR
    input [WIDTH:0] res;//33 bit result register
    begin
        `CARRY = res[WIDTH];
        `EVEN = ~res[0];
        `PARITY = ^res;
        `ZERO = ~(|res);
        `NEG = res [WIDTH-1];
        setcondcode = 8;//debug<!>
    end
endfunction//setcondcode

function [WIDTH-1:0] getsrc;
    input [WIDTH-1:0] in;
    begin
        if(`SRCTYPE == `REGTYPE) getsrc = RFILE[`SRC];//reg
        else getsrc = `SRC;//imm. type
    end
endfunction//getsrc

function [WIDTH-1:0] getdst;
    input [WIDTH-1:0] in;
    begin
        if(`DSTTYPE == `REGTYPE) begin
            getdst = RFILE[`DST];//reg
        end else begin
            //ERROR imm. type
            debug_r = 10;
            getdst = 0;
        end
    end
    
endfunction//getdst

//negedge -> do fetch
always @(negedge clk)
begin
	ir = INS_MEM;
end

always @(posedge clk or posedge rst)
begin//always @(posedge clk or posedge rst)
    if (rst) begin
        debug_r = 2;
        //initialization
        for (i = 0; i<MAXREGS; i=i+1/*0~16*/) begin
            RFILE[i] = 0;
        end
        ir = 0;
        src1 = 0;
        src2 = 0;
        result = 0;
        psr = 0;
        pc = 0;
        MEM_D = 0;
        //INS_D = 0;//<X>
        MEM_O = 0;
        temp_checkcond = 0;
        MEM_C = 0;
        //-------------------
        reg_debug_o = 0;
        //-------------------
 
    end else begin
        //make mem. unreadable
        MEM_C = 0;
        //fetch
        //ir = INS_MEM;
        //INS_D = pc+1;//<X>
        pc = pc+1;
        //execute
        case (`OPCODE/*ir...*/)
            /*0*/`NOP: begin
                debug_r = 3;
            end
            /*1*/`BRA: begin
                //function checkcond; //Returns 1 if condition code is set .
                //input [4:0] ccode;
                case (`CCODE)
                /*================Grammar description================
                CCODE is "part of OPCODE" (4 bits)
                it has 5 different state (Just like the abbreviation written below)
                eg.: CCC | CCE | CCP ...etc
                for every case/state of CCODE been asked for,
                we want to go and find the corresponding state memory,
                and see if this state is set (is true),
                this led to the appearance of the "equal to one" judgment.
                ======END=======Grammar description========END=====*/
                    `CCC: temp_checkcond = `CARRY;
                    `CCE: temp_checkcond = `EVEN;
                    `CCP: temp_checkcond = `PARITY;
                    `CCZ: temp_checkcond = `ZERO;
                    `CCN: temp_checkcond = `NEG;
                    `CCA: temp_checkcond = 1;//always
                    default: debug_r = 6 ;
                endcase
                if (temp_checkcond) begin
                    if (debug) begin
                        debug_r=9;
                    end else begin
                        debug_r=0;
                    end
                    pc = `DST;
                end else begin
                    debug_r = 7 ;
                end
            end
            /*2*/`LD: begin
                psr = 0;//clearcondcode
                MEM_D = `SRC;
                RFILE[`DST] = (`SRCTYPE)?`SRC/*SRCTYPE=1 :imm*/:MEM_IN;
                debug_r = setcondcode({1'b0,RFILE[`DST]}/*33bits*/);
            end
            /*3*/`STR: begin
                psr = 0;//clearcondcode
                MEM_C = 1;//let MEM do "write"
                MEM_D = `DST;
                MEM_O = (`SRCTYPE)?`SRC/*SRCTYPE=1 :imm*/:RFILE[`SRC];
                debug_r = (`SRCTYPE)?setcondcode({21'b0, `SRC/*12bit, imm*/}):setcondcode({1'b0, RFILE[`SRC]});
            end
            /*4*/`ADD: begin
                //debug_r =104;
                psr = 0;//clearcondcode
                src1 = getsrc(ir);
                src2 = getdst(ir);
                result = src1+src2;
                debug_r = setcondcode(result);
            end
            /*5*/`MUL: begin
                //debug_r =105;
                psr = 0;//clearcondcode
                src1 = getsrc(ir);
                src2 = getdst(ir);
                result = src1*src2;
                debug_r = setcondcode(result);
            end
            /*6*/`CMP: begin
                //debug_r =106;
                psr = 0;//clearcondcode
                src1 = getsrc(ir);
                result = ~src1;
                debug_r = setcondcode(result);
            end
            /*7*/`SHF: begin
                //debug_r =107;
                psr = 0;//clearcondcode
                src1 = getsrc(ir);
                src2 = getdst(ir);
                result = (src1[ADDRSIZE-1:0] >= 0)?(src2>>src1[ADDRSIZE-1:0]):(src2<<src1[ADDRSIZE-1:0]);
                debug_r = setcondcode(result);
                /*The input terminal (source) of the rotation / offset command can be 
                a "register" or "direct number". 
                However, if the "direct number" is the source,
                 the maximum expressible size is 
                 "the size of ADDR (12)" 
                 So use the sign of the last 12 yards of the 
                 judgment source to decide whether to turn left or right*/
            end
            /*8*/`ROT: begin
                //debug_r =108;
                psr = 0;//clearcondcode
                src1 = getsrc(ir);
                src2 = getdst(ir);
                if (~src1[ADDRSIZE-1/*:0*/]/*>=0*//*right*/) begin
                    //result[WIDTH-1:WIDTH-1-src1[ADDRSIZE-1:0]]=src2[0:src1[ADDRSIZE-1:0]-1];
                    result = ( src2 >> src1[ADDRSIZE-1:0] ) | ( src2 << ( WIDTH -src1[ADDRSIZE-1:0] ) );
                end else begin/*left*/
                    //bit_rotate_left
                    //Bitwise or not equal to||
                    result[32]=0;
                    result[31:0] = ( src2 << ( -src1[ADDRSIZE-1:0] ) ) | ( src2 >> ( WIDTH -( -src1[ADDRSIZE-1:0] ) ) );
                    //result=33'b000000000000000000000000000000001;
                    //debug_r=0;
                end
                debug_r = setcondcode(result);
                    //debug_r=(src1[ADDRSIZE-1:0])?1:0;
                    //reg_debug_o=( src2 << ( -src1[ADDRSIZE-1:0] ) ) | ( src2 >> ( WIDTH -( -src1[ADDRSIZE-1:0] ) ) );
                    //reg_debug_o=(src1[ADDRSIZE-1:0])?1:0;
            end
            /*9*/`HLT: begin
                debug_r = 5;
            end
            /*10*/`DIV: begin
                debug_r =110;
            end
            /*11*/`RMD: begin
                debug_r =111;
            end
            default: begin
                debug_r = 4;
            end
        endcase
        //write_result
        /*you can't put debug_r here //debug_r = 11;*/
        if (
            (`OPCODE == `ADD) ||//4
            (`OPCODE == `MUL) ||//5
            (`OPCODE == `CMP) ||//6
            (`OPCODE == `SHF) ||//7
            (`OPCODE == `ROT) ||//8
            (`OPCODE == `DIV) ||//10 Division
            (`OPCODE == `RMD)//11 Remainder
        ) begin
            if (`DSTTYPE == `REGTYPE) begin
                RFILE[`DST] = result;
            end else begin
                MEM_C = 1;
                MEM_O = result[WIDTH-1:0];
            end
        end else begin
            /*<!I'm not sure if this thing is right>*/
            RFILE[`DST] = RFILE[`DST];
            MEM_C = MEM_C;
            MEM_O = MEM_O;
            //debug_r = 11;//don't need do anything write_result
        end
    end
end//always @(posedge clk or posedge rst)

endmodule // instruction_set_model
/*
debug_r code 
0:undefine
2:[run rst.]
3:[exe. NOP]
4:[can't find ins.]go into default @ case(OPCODE)
5:[ext. HLT]need do:$display("Halt");$stop;
6:go in default @ [case (`CCODE)]
7:[sataus reg. Status is different from demand] @ BRA
8:[do SETCONDCODE]
9:branch, true, do change pc
10:$display("Error:Immediate data can’t be destination.");
//11:[don't need do anything] @ write_result
//104:opcode case = 4
//105:opcode case = 5
//106:opcode case = 6
//107:opcode case = 7
//108:opcode case = 8
110:opcode case = 10
111:opcode case = 11
*/

tb.v
`timescale 1ns/1ps
`include "cpu.v"
//%%%%%%%%%%%%%%%%%%%%%%%%%%%%%%%%%%%%%%%%%%%%%%%%%%%%%%%%%%%%%%%%%
//`include "tsmc18.v"
`default_nettype none

module tb_cpu;
parameter WIDTH = 32;//width of data path
parameter ADDRSIZE = 12;//size of address field
parameter MEMSIZE = (1<<ADDRSIZE/*4096*/);//size of memory (2^ADDRSIZE)=2^12
parameter Forced_stop_number_of_cycles = 20;
//main reg
reg [WIDTH-1:0] MEM[0:MEMSIZE-1];//MEMORY
reg [WIDTH-1:0] I_MEM[0:MEMSIZE-1];//ins. mem.

reg clk;
reg rst;
reg debug;
wire [6:0] debuger;
wire [11:0] MEM_ADDR;
reg [0:31] MEM_IN;
wire [0:31] MEM_OUT;
wire MEM_CTRL;
wire [11:0] INS_ADDR;
reg [0:31] INS_MEM;

//-------------------------------------
wire [32:0] reg_debug_out;
//-------------------------------------

//debug
integer tb_debug;
integer ot_mem=0;

instruction_set_model cpu 
(
    .rst (rst),
    .clk (clk),
    .debug(debug),
    .debuger(debuger),
    .MEM_ADDR(MEM_ADDR),
    .MEM_IN(MEM_IN),
    .MEM_OUT(MEM_OUT),
    .MEM_CTRL(MEM_CTRL),
    .INS_ADDR(INS_ADDR),
    .INS_MEM(INS_MEM),
    .reg_debug_out(reg_debug_out)
);

always @(MEM_ADDR) begin : always_MEM_ADDR
    MEM_IN = MEM[MEM_ADDR];
end

always @(INS_ADDR) begin : always_INS_ADDR
    INS_MEM = I_MEM[INS_ADDR];
end

always @(MEM_OUT) begin : always_MEM_OUT
    if (MEM_CTRL) begin
        MEM[MEM_ADDR] = MEM_OUT;
    end else begin
        tb_debug = 1;
    end
end

localparam CLK_PERIOD = 100;
always #(CLK_PERIOD/2) clk=~clk;

/*
initial begin
    dumpfile("tb_cpu.vcd");
    dumpvars(0, tb_cpu);
end
*/

initial begin : monitor
    $monitor($time," | rst=%b | debug=%b | debuger=%d | MEM_ADDR=%d | MEM_IN=%d | MEM_OUT=%d | MEM_CTRL=%d | INS_ADDR=%d | INS_MEM=%b  |  tb_debug=%d  |  reg_debug_out=%b",rst,debug,debuger,MEM_ADDR,MEM_IN,MEM_OUT,MEM_CTRL,INS_ADDR,INS_MEM,tb_debug,reg_debug_out);
end

always@(debuger) begin : stop
    if (debuger==5) begin
    $display("=================================================");
    for ( ot_mem= 0; ot_mem<10; ot_mem=ot_mem+1) begin
        $display("data_MEM[%d]=%d",ot_mem,MEM[ot_mem]);
    end
    $display("=================================================");
        $display("Halt...");
        $finish;
    end
end

initial begin : main_loop
    #1 rst<=1'b0;clk<=1'b0;
    debug<=1;MEM_IN<=0;INS_MEM<=0;
    #(CLK_PERIOD) rst<=1;
    #(CLK_PERIOD) rst<=0;clk<=0;

    $display("=================================================");
    for ( ot_mem= 0; ot_mem<10; ot_mem=ot_mem+1) begin
        $display("I_MEM[%d]=%b",ot_mem,I_MEM[ot_mem]);
    end
    $display("=================================================");

    #(CLK_PERIOD*Forced_stop_number_of_cycles) $finish;
end

//%%%%%%%%%%%%%%%%%%%%%%%%%%%%%%%%%%%%%%%%%%%%%%%%%%%%%%%%%%%%%%%%%%%%%%%%%%%%%%%
initial 
begin
//$sdf_annotate ("sy_cpu.sdf", cpu);
$dumpfile("cpu.vcd");
$dumpvars;
end

initial begin : prog_load
    $readmemb("mem.prog",MEM);
    $readmemb("i_mem.prog",I_MEM);
end

endmodule
`default_nettype wire
/*tb_debug code
1:MEM_OUT changed, but MEM_CTRL is not set

*/

cpu.vcd
$date
	Thu Dec 26 23:21:51 2019
$end
$version
	Icarus Verilog
$end
$timescale
	1ps
$end
$scope module tb_cpu $end
$var wire 33 ! reg_debug_out [32:0] $end
$var wire 7 " debuger [6:0] $end
$var wire 32 # MEM_OUT [0:31] $end
$var wire 1 $ MEM_CTRL $end
$var wire 12 % MEM_ADDR [11:0] $end
$var wire 12 & INS_ADDR [11:0] $end
$var reg 32 ' INS_MEM [0:31] $end
$var reg 32 ( MEM_IN [0:31] $end
$var reg 1 ) clk $end
$var reg 1 * debug $end
$var reg 1 + rst $end
$var integer 32 , ot_mem [31:0] $end
$var integer 32 - tb_debug [31:0] $end
$scope module cpu $end
$var wire 12 . INS_ADDR [11:0] $end
$var wire 32 / INS_MEM [0:31] $end
$var wire 12 0 MEM_ADDR [11:0] $end
$var wire 1 $ MEM_CTRL $end
$var wire 32 1 MEM_IN [0:31] $end
$var wire 32 2 MEM_OUT [0:31] $end
$var wire 1 ) clk $end
$var wire 1 * debug $end
$var wire 7 3 debuger [6:0] $end
$var wire 33 4 reg_debug_out [32:0] $end
$var wire 1 + rst $end
$var reg 1 5 MEM_C $end
$var reg 12 6 MEM_D [11:0] $end
$var reg 32 7 MEM_O [0:31] $end
$var reg 7 8 debug_r [6:0] $end
$var reg 32 9 ir [31:0] $end
$var reg 12 : pc [11:0] $end
$var reg 5 ; psr [4:0] $end
$var reg 33 < reg_debug_o [32:0] $end
$var reg 33 = result [32:0] $end
$var reg 32 > src1 [31:0] $end
$var reg 32 ? src2 [31:0] $end
$var reg 1 @ temp_checkcond $end
$var integer 32 A i [31:0] $end
$scope function getdst $end
$var reg 32 B getdst [31:0] $end
$var reg 32 C in [31:0] $end
$upscope $end
$scope function getsrc $end
$var reg 32 D getsrc [31:0] $end
$var reg 32 E in [31:0] $end
$upscope $end
$scope function setcondcode $end
$var reg 33 F res [32:0] $end
$var reg 7 G setcondcode [6:0] $end
$upscope $end
$upscope $end
$scope begin always_INS_ADDR $end
$upscope $end
$scope begin always_MEM_ADDR $end
$upscope $end
$scope begin always_MEM_OUT $end
$upscope $end
$scope begin main_loop $end
$upscope $end
$scope begin monitor $end
$upscope $end
$scope begin prog_load $end
$upscope $end
$scope begin stop $end
$upscope $end
$upscope $end
$enddefinitions $end
#0
$dumpvars
bx G
bx F
bx E
bx D
bx C
bx B
bx A
x@
bx ?
bx >
bx =
bx <
bx ;
bx :
bx 9
bx 8
bx 7
bx 6
x5
bx 4
bx 3
bx 2
bx 1
bx 0
bx /
bx .
bx -
b0 ,
x+
x*
x)
bx (
bx '
bx &
bx %
x$
bx #
bx "
bx !
$end
#1000
b0 9
b0 '
b0 /
b0 (
b0 1
1*
0)
0+
#5000
b1 -
b0 !
b0 4
b0 <
0$
05
0@
b0 #
b0 2
b0 7
b0 %
b0 0
b0 6
b0 &
b0 .
b0 :
b0 ;
b0 =
b0 ?
b0 >
b10000 A
b10 "
b10 3
b10 8
1+
#9000
0+
b1010 ,
#50000
b101000000000000011000000000001 '
b101000000000000011000000000001 /
b11 "
b11 3
b11 8
b1 &
b1 .
b1 :
1)
#100000
b101000000000000011000000000001 9
0)
#150000
bx (
bx 1
b10001000111111111111000000000001 '
b10001000111111111111000000000001 /
b1000 "
b1000 3
b1000 8
b1000 G
b11 F
b11 %
b11 0
b11 6
b10 &
b10 .
b10 :
1)
#200000
b10001000111111111111000000000001 9
0)
#250000
b110000000000000001000000000000 '
b110000000000000001000000000000 /
b10 ;
b110 F
b110 =
b11 ?
b11 B
b10001000111111111111000000000001 C
b111111111111 >
b111111111111 D
b10001000111111111111000000000001 E
b11 &
b11 .
b11 :
1)
#300000
b110000000000000001000000000000 9
0)
#350000
b0 (
b0 1
b10010000000000000000000000000000 '
b10010000000000000000000000000000 /
b110 #
b110 2
b110 7
b0 %
b0 0
b0 6
1$
15
b10 ;
b100 &
b100 .
b100 :
1)
#400000
b10010000000000000000000000000000 9
0)
#450000
b1010 ,
bx '
bx /
b101 "
b101 3
b101 8
b101 &
b101 .
b101 :
0$
05
1)
