clk_test.v
module clk_test(
    input clk,
    input rst,
    input [15:0] data_in,
    output [15:0] data_out
);
reg [15:0] R_data_out;
assign data_out=R_data_out;
always@(posedge clk)begin
    if(rst)begin
       R_data_out = 0;
    end else begin
    if (data_in > 10) begin
        R_data_out = 5;
    end else begin
R_data_out=3;
end
    end
end


endmodule // clk_test

clk_tb.v
`include "clk_test.v"
`default_nettype none

module tb_clk_test;
reg clk;
reg rst;
reg [15:0] data_in;
wire [15:0] data_out;

clk_test clk_t
(
    .rst (rst),
    .clk (clk),
    .data_in (data_in),
    .data_out (data_out)
);

localparam CLK_PERIOD = 10;
always #(CLK_PERIOD/2) clk=~clk;

/*
initial begin
    dumpfile("tb_clk_test.vcd");
    dumpvars(0, tb_clk_test);
end
*/

initial begin
    #1 rst<=1'bx;clk<=1'bx;
    data_in=0;
    #(CLK_PERIOD*3) rst<=1;
    #(CLK_PERIOD*3) rst<=0;clk<=0;
    #(CLK_PERIOD*3) data_in=1;
    #(CLK_PERIOD*3) data_in=12;
    #(CLK_PERIOD*3) $finish;
end

initial begin : monitor
    $monitor($time,"  |  in=%d  |  out=%d",data_in,data_out);
end

endmodule
`default_nettype wire

tb_clk_test.vcd
$date
	Sat Dec 21 14:52:26 2019
$end
$version
	Icarus Verilog
$end
$timescale
	1ps
$end
$scope module tb_clk_test $end
$var wire 16 ! data_out [15:0] $end
$var reg 1 " clk $end
$var reg 16 # data_in [15:0] $end
$var reg 1 $ rst $end
$scope module clk_t $end
$var wire 1 " clk $end
$var wire 16 % data_in [15:0] $end
$var wire 16 & data_out [15:0] $end
$var wire 1 $ rst $end
$var reg 16 ' R_data_out [15:0] $end
$upscope $end
$scope begin monitor $end
$upscope $end
$upscope $end
$enddefinitions $end
#0
$dumpvars
bx '
bx &
bx %
x$
bx #
x"
bx !
$end
#1000
b0 #
b0 %
#31000
1$
#61000
0"
0$
#65000
b11 !
b11 &
b11 '
1"
#70000
0"
#75000
1"
#80000
0"
#85000
1"
#90000
0"
#91000
b1 #
b1 %
#95000
1"
#100000
0"
#105000
1"
#110000
0"
#115000
1"
#120000
0"
#121000
b1100 #
b1100 %
#125000
b101 !
b101 &
b101 '
1"
#130000
0"
#135000
1"
#140000
0"
#145000
1"
#150000
0"
#151000
b11 #
b11 %
#155000
b11 !
b11 &
b11 '
1"
